bclearer_core/__init__.py
bclearer_core/bie/__init__.py
bclearer_core/bie/domain/__init__.py
bclearer_core/bie/domain/bie_domain_objects.py
bclearer_core/bie/infrastructure/__init__.py
bclearer_core/bie/infrastructure/bie_infrastructure_objects.py
bclearer_core/bie/infrastructure/types/__init__.py
bclearer_core/bie/infrastructure/types/bie_common_column_names.py
bclearer_core/bie/top/__init__.py
bclearer_core/bie/top/bie_objects.py
bclearer_core/ckids/__init__.py
bclearer_core/ckids/boro_object_ckids.py
bclearer_core/ckids/place_number_type_ckids.py
bclearer_core/common_knowledge/__init__.py
bclearer_core/common_knowledge/adjustment_operation_types.py
bclearer_core/common_knowledge/attribute_to_associations_operation_subtypes.py
bclearer_core/common_knowledge/bclearer_additional_column_types.py
bclearer_core/common_knowledge/bclearer_constants.py
bclearer_core/common_knowledge/bclearer_matched_ea_objects.py
bclearer_core/common_knowledge/content_operation_types.py
bclearer_core/common_knowledge/convention_shift_operation_types.py
bclearer_core/common_knowledge/digitialisation_level_stereotype_matched_ea_objects.py
bclearer_core/common_knowledge/matched_objects.py
bclearer_core/common_knowledge/operation_types.py
bclearer_core/common_knowledge/universe_modification_operation_types.py
bclearer_core/configuration_managers/__init__.py
bclearer_core/configuration_managers/configuration_loader.py
bclearer_core/configurations/__init__.py
bclearer_core/configurations/add_dependency_to_instances_of_type_configuration_objects.py
bclearer_core/configurations/add_dependency_to_instances_of_type_configurations.py
bclearer_core/configurations/adjustment_operation_configurations.py
bclearer_core/configurations/adjustment_operations_substage_configurations.py
bclearer_core/configurations/attribute_name_to_name_object_configuration_objects.py
bclearer_core/configurations/attribute_to_association_adjustment_operation_configurations.py
bclearer_core-0.1.10.dist-info/METADATA
bclearer_core-0.1.10.dist-info/WHEEL
bclearer_core-0.1.10.dist-info/licenses/LICENSE.md
bclearer_core-0.1.10.dist-info/RECORD
