Metadata-Version: 2.4
Name: bclearer-core
Version: 0.1.10
Author-email: Mesbah Khan <khanm@ontoledgy.io>
License-File: LICENSE.md
Requires-Python: >=3.12
